koch_trainer/__init__.py
koch_trainer/koch_trainer.py
koch_trainer/static/callsigns.txt
koch_trainer/static/english-all.txt
koch_trainer/static/english-long.txt
koch_trainer/static/english.txt
koch_trainer-0.0.5.dist-info/LICENSE
koch_trainer-0.0.5.dist-info/METADATA
koch_trainer-0.0.5.dist-info/WHEEL
koch_trainer-0.0.5.dist-info/entry_points.txt
koch_trainer-0.0.5.dist-info/top_level.txt
koch_trainer-0.0.5.dist-info/RECORD
