Metadata-Version: 2.1
Name: koch-trainer
Version: 0.0.5
Summary: Koch method Morse code training program with Word Mode, Callsign Mode, and Random Character Mode
Home-page: https://github.com/rguisewite/koch_trainer
Author: Ryan Guisewite
Author-email: ryan.guisewite@gmail.com
License: UNKNOWN
Platform: UNKNOWN
Classifier: Environment :: Console
Classifier: Topic :: Multimedia :: Sound/Audio
Classifier: Topic :: Communications :: Ham Radio
Classifier: Programming Language :: Python :: 3.9
Requires-Dist: audiogen-p3
Requires-Dist: PyAudio
